libcom/__init__.py
libcom/color_transfer/__init__.py
libcom/color_transfer/reinhard.py
libcom/fopa_heat_map/__init__.py
libcom/fopa_heat_map/fopa_heat_map.py
libcom/fopa_heat_map/source/__init__.py
libcom/fopa_heat_map/source/prepare_multi_fg_scales.py
libcom/fopa_heat_map/source/backbone/ResNet.py
libcom/fopa_heat_map/source/backbone/__init__.py
libcom/fopa_heat_map/source/data/OBdataset.py
libcom/fopa_heat_map/source/data/__init__.py
libcom/fopa_heat_map/source/data/all_transforms.py
libcom/fopa_heat_map/source/network/BaseBlocks.py
libcom/fopa_heat_map/source/network/DynamicModules.py
libcom/fopa_heat_map/source/network/ObPlaNet_simple.py
libcom/fopa_heat_map/source/network/__init__.py
libcom/fopa_heat_map/source/network/tensor_ops.py
libcom/fos_score/__init__.py
libcom/fos_score/fos_score_prediction.py
libcom/fos_score/source/__init__.py
libcom/fos_score/source/loss_function.py
libcom/fos_score/source/networks.py
libcom/fos_score/source/config/__init__.py
libcom/fos_score/source/config/config.py
libcom/fos_score/source/config/config.sfosd.yaml
libcom/fos_score/source/config/config_rfosd.yaml
libcom/harmony_score/__init__.py
libcom/harmony_score/harmony_score_prediction.py
libcom/harmony_score/source/__init__.py
libcom/harmony_score/source/bargainnet.py
libcom/image_harmonization/__init__.py
libcom/image_harmonization/image_harmonization.py
libcom/image_harmonization/source/__init__.py
libcom/image_harmonization/source/cdt_net.py
libcom/image_harmonization/source/functions.py
libcom/image_harmonization/source/pct_net.py
libcom/inharmonious_region_localization/__init__.py
libcom/inharmonious_region_localization/inharmonious_region_localization.py
libcom/inharmonious_region_localization/source/__init__.py
libcom/inharmonious_region_localization/source/blocks.py
libcom/inharmonious_region_localization/source/functions.py
libcom/inharmonious_region_localization/source/madis_net.py
libcom/insert_anything/__init__.py
libcom/insert_anything/insert_anything.py
libcom-0.1.4.dist-info/licenses/LICENSE
libcom-0.1.4.dist-info/METADATA
libcom-0.1.4.dist-info/WHEEL
libcom-0.1.4.dist-info/top_level.txt
libcom-0.1.4.dist-info/RECORD
