Metadata-Version: 2.4
Name: libcom
Version: 0.1.4
Summary: Image Composition Toolbox
Home-page: https://github.com/bcmi/libcom
Author: BCMI Lab
Author-email: bernard-zhang@hotmail.com
License: Apache License 2.0
Keywords: computer vision,image composition
Classifier: License :: OSI Approved :: Apache Software License
Classifier: Operating System :: OS Independent
Classifier: Programming Language :: Python :: 3
Classifier: Programming Language :: Python :: 3.8
License-File: LICENSE
Requires-Dist: einops
Requires-Dist: huggingface_hub
Requires-Dist: imageio
Requires-Dist: torch==2.6.0
Requires-Dist: torchvision==0.21.0
Requires-Dist: diffusers==0.34.0
Requires-Dist: mmdet==3.2.0
Requires-Dist: mmpose==1.2.0
Requires-Dist: peft
Requires-Dist: sentencepiece
Requires-Dist: protobuf
Requires-Dist: modelscope
Requires-Dist: omegaconf
Requires-Dist: opencv_python
Requires-Dist: opencv_python_headless
Requires-Dist: pytorch_lightning
Requires-Dist: transformers
Requires-Dist: tqdm
Requires-Dist: open_clip_torch
Requires-Dist: taming-transformers-rom1504
Requires-Dist: scikit-learn
Dynamic: author
Dynamic: author-email
Dynamic: classifier
Dynamic: description
Dynamic: description-content-type
Dynamic: home-page
Dynamic: keywords
Dynamic: license
Dynamic: license-file
Dynamic: requires-dist
Dynamic: summary
